django_vox/__init__.py
django_vox/activity_urls.py
django_vox/admin.py
django_vox/apps.py
django_vox/base.py
django_vox/middleware.py
django_vox/models.py
django_vox/registry.py
django_vox/settings.py
django_vox/views.py
django_vox/backends/__init__.py
django_vox/backends/activity.py
django_vox/backends/base.py
django_vox/backends/base_email.py
django_vox/backends/html_email.py
django_vox/backends/json_webhook.py
django_vox/backends/markdown_email.py
django_vox/backends/postmark_email.py
django_vox/backends/slack.py
django_vox/backends/template_email.py
django_vox/backends/twilio.py
django_vox/backends/twitter.py
django_vox/backends/xmpp.py
django_vox/extra/__init__.py
django_vox/extra/background.py
django_vox/extra/background_tasks.py
django_vox/management/__init__.py
django_vox/management/commands/__init__.py
django_vox/management/commands/make_notifications.py
django_vox/migrations/0001_initial.py
django_vox/migrations/0002_attachments.py
django_vox/migrations/0003_activity_stream.py
django_vox/migrations/0004_activity_fields.py
django_vox/migrations/0005_activity_table.py
django_vox/migrations/0006_activity_read_at.py
django_vox/migrations/0007_from_address.py
django_vox/migrations/0008_notification_last_updated.py
django_vox/migrations/__init__.py
django_vox/static/django_vox/notification_fields.js
django_vox/static/django_vox/markitup/images.css
django_vox/static/django_vox/markitup/jquery.markitup.js
django_vox/static/django_vox/markitup/style.css
django_vox/static/django_vox/markitup/images/bold.png
django_vox/static/django_vox/markitup/images/code.png
django_vox/static/django_vox/markitup/images/handle.png
django_vox/static/django_vox/markitup/images/image.png
django_vox/static/django_vox/markitup/images/italic.png
django_vox/static/django_vox/markitup/images/link.png
django_vox/static/django_vox/markitup/images/list-bullet.png
django_vox/static/django_vox/markitup/images/list-numeric.png
django_vox-4.0.6.dist-info/DESCRIPTION.rst
django_vox-4.0.6.dist-info/METADATA
django_vox-4.0.6.dist-info/RECORD
django_vox-4.0.6.dist-info/WHEEL
django_vox-4.0.6.dist-info/metadata.json
django_vox-4.0.6.dist-info/top_level.txt
