Metadata-Version: 2.0
Name: django-vox
Version: 4.0.6
Summary: A notification app for Django
Home-page: https://gitlab.com/alantrick/django-vox
Author: Alan Trick
Author-email: me@alantrick.ca
License: LGPL3+
Project-URL: Bug Tracker, https://gitlab.com/alantrick/django-vox/issues
Project-URL: Documentation, https://alantrick.gitlab.io/django-vox/
Project-URL: Source Code, https://gitlab.com/alantrick/django-vox
Keywords: notifications email twilio slack
Platform: UNKNOWN
Classifier: Development Status :: 5 - Production/Stable
Classifier: Environment :: Web Environment
Classifier: Framework :: Django
Classifier: Intended Audience :: Developers
Classifier: License :: OSI Approved :: GNU Lesser General Public License v3 or later (LGPLv3+)
Classifier: Operating System :: OS Independent
Classifier: Programming Language :: Python
Classifier: Programming Language :: Python :: 3.6
Classifier: Framework :: Django
Classifier: Framework :: Django :: 1.11
Classifier: Framework :: Django :: 2.0
Classifier: Framework :: Django :: 2.1
Classifier: Framework :: Django :: 2.2
Classifier: Topic :: Utilities
Requires-Python: >=3.6
Provides-Extra: twitter
Provides-Extra: twilio
Provides-Extra: test
Provides-Extra: markdown
Provides-Extra: docs
Provides-Extra: xmpp
Requires-Dist: Django (>=1.11)
Requires-Dist: requests
Requires-Dist: lxml
Requires-Dist: python-dateutil
Requires-Dist: august (>=2.1)
Requires-Dist: dataclasses
Requires-Dist: aspy (>=0.4)
Provides-Extra: docs
Requires-Dist: sphinx; extra == 'docs'
Requires-Dist: sphinx-rtd-theme; extra == 'docs'
Requires-Dist: django-background-tasks; extra == 'docs'
Provides-Extra: markdown
Requires-Dist: markdown2; extra == 'markdown'
Provides-Extra: test
Requires-Dist: pytest (>=5.2); extra == 'test'
Requires-Dist: pytest-django; extra == 'test'
Requires-Dist: pytest-cov; extra == 'test'
Requires-Dist: pytest-pythonpath; extra == 'test'
Requires-Dist: tox; extra == 'test'
Requires-Dist: beautifulsoup4; extra == 'test'
Requires-Dist: pyyaml; extra == 'test'
Requires-Dist: django-background-tasks; extra == 'test'
Provides-Extra: twilio
Requires-Dist: twilio; extra == 'twilio'
Provides-Extra: twitter
Requires-Dist: python-twitter; extra == 'twitter'
Provides-Extra: xmpp
Requires-Dist: sleekxmpp; extra == 'xmpp'
Requires-Dist: dnspython; extra == 'xmpp'
